yt_dlp_plugins/extractor/ytpot_jsi.py
yt_dlp_plugins/getpot_phantomjs/__init__.py
yt_dlp_plugins/getpot_phantomjs/_script.py
yt_dlp_plugins/getpot_phantomjs/debug.py
yt_dlp_plugins/getpot_phantomjs/fetch_pot.py
yt_dlp_plugins/getpot_phantomjs/phantom_jsi.py
yt_dlp_plugins/getpot_phantomjs/script.py
yt_dlp_plugins/getpot_phantomjs/server.py
yt_dlp_plugins/getpot_phantomjs/utils.py
yt_dlp_getpot_jsi-0.3.1.dist-info/METADATA
yt_dlp_getpot_jsi-0.3.1.dist-info/WHEEL
yt_dlp_getpot_jsi-0.3.1.dist-info/RECORD
