Metadata-Version: 2.4
Name: yt-dlp-getpot-jsi
Version: 0.3.1
Maintainer: grqz
Keywords: yt-dlp,yt-dlp-plugin,yt-dlp-pot-provider
Requires-Python: >=3.9
